Metadata-Version: 2.4
Name: lightnovel-crawler
Version: 3.10.1
Summary: Download lightnovels from various online sources and generate output in different formats, e.g. epub, mobi, json, html, text, docx, pdf etc.
Author-email: Sudipto Chandra <dipu.sudipta@gmail.com>
License:                     GNU GENERAL PUBLIC LICENSE
Project-URL: Documentation, https://github.com/dipu-bd/lightnovel-crawler/blob/master/README.md
Project-URL: Issue Tracker, https://github.com/dipu-bd/lightnovel-crawler/issues
Project-URL: Source Code, https://github.com/dipu-bd/lightnovel-crawler
Keywords: lightnovel,crawler,lncrawl,novel,pdf,epub,mobi,scraper
Classifier: Development Status :: 5 - Production/Stable
Classifier: Natural Language :: English
Classifier: Intended Audience :: Developers
Classifier: Topic :: Games/Entertainment
Classifier: Environment :: Console
Classifier: Programming Language :: Python :: 3 :: Only
Classifier: Programming Language :: Python :: 3.8
Classifier: Programming Language :: Python :: 3.9
Classifier: Programming Language :: Python :: 3.10
Classifier: Programming Language :: Python :: 3.11
Classifier: Programming Language :: Python :: 3.12
Classifier: Programming Language :: Python :: 3.13
Requires-Python: >=3.8
License-File: LICENSE
Requires-Dist: typer
Requires-Dist: ascii
Requires-Dist: regex
Requires-Dist: packaging
Requires-Dist: html-clean
Requires-Dist: lxml<6.0.0,>=5.4.0
Requires-Dist: pyease-grpc>=1.6.0
Requires-Dist: python-dotenv<2.0.0,>=0.15.0
Requires-Dist: beautifulsoup4<5.0.0,>=4.8.0
Requires-Dist: requests<2.33.0,>=2.20.0
Requires-Dist: python-slugify<9.0.0,>=4.0.0
Requires-Dist: colorama<0.5.0,>=0.4.0
Requires-Dist: tqdm<5.0,>=4.60
Requires-Dist: PyExecJS<2.0.0,>=1.5.1
Requires-Dist: ebooklib<1.0.0,>=0.17.0
Requires-Dist: pillow>=6.0.0
Requires-Dist: cloudscraper>=1.2.71
Requires-Dist: readability-lxml<1.0.0,>=0.8.0
Requires-Dist: questionary>=1.6.0
Requires-Dist: prompt-toolkit~=3.0
Requires-Dist: html5lib~=1.1
Requires-Dist: base58~=2.1.1
Requires-Dist: python-box<8.0.0,>=6.0.0
Requires-Dist: pycryptodome<4.0.0,>=3.0.0
Requires-Dist: selenium>=3.141.0
Requires-Dist: tenacity>=9.0.0
Requires-Dist: discord.py>=2.0.0
Requires-Dist: python-telegram-bot[job-queue]~=20.0
Requires-Dist: uvicorn
Requires-Dist: fastapi[standard]
Requires-Dist: cachetools
Requires-Dist: sqlmodel
Requires-Dist: passlib[argon2]
Requires-Dist: python-jose[cryptography]
Requires-Dist: python-dateutil
Requires-Dist: wheel
Requires-Dist: build
Requires-Dist: black
Requires-Dist: flake8
Requires-Dist: tk-tools
Requires-Dist: setuptools>=61.0
Requires-Dist: pyinstaller
Requires-Dist: types-tqdm
Requires-Dist: types-colorama
Requires-Dist: types-cachetools
Requires-Dist: types-python-dateutil
Requires-Dist: types-passlib
Requires-Dist: types-python-jose
Requires-Dist: types-setuptools
Requires-Dist: lxml-stubs
Dynamic: license-file
